js_code/__init__.py
js_code/js_tools.py
js_code-2.0.0.dist-info/LICENSE
js_code-2.0.0.dist-info/METADATA
js_code-2.0.0.dist-info/WHEEL
js_code-2.0.0.dist-info/top_level.txt
js_code-2.0.0.dist-info/RECORD
