Metadata-Version: 2.1
Name: js-code
Version: 2.0.0
Summary: A simple library to run JavaScript code based on Python
Home-page: https://github.com/aduh5821/js_code.git
Author: Aduh
Author-email: aduh73285@gmail.com
License: BSD 2-Clause License        
Platform: UNKNOWN
Classifier: Programming Language :: Python :: 3
Classifier: License :: OSI Approved :: BSD License
Classifier: Operating System :: OS Independent
Requires-Python: >=3.6
License-File: LICENSE
Requires-Dist: PyExecJS2
